zwiftpktmon/__init__.py
zwiftpktmon/async_monitor.py
zwiftpktmon/events.py
zwiftpktmon/zwift_messages_pb2.py
zwiftpktmon-0.1.0.dist-info/LICENSE
zwiftpktmon-0.1.0.dist-info/METADATA
zwiftpktmon-0.1.0.dist-info/WHEEL
zwiftpktmon-0.1.0.dist-info/top_level.txt
zwiftpktmon-0.1.0.dist-info/RECORD
