Metadata-Version: 2.1
Name: zwiftpktmon
Version: 0.1.0
Summary: A Python port of the C# ZwiftPacketMonitor project which monitors Zwift UDP packets
Home-page: https://github.com/vincentdavis/zwifty-packets
Author: Kevin Ruff
Author-email: ruff.kevin@outlook.com
License: UNKNOWN
Project-URL: Bug Tracker, https://github.com/vincentdavis/zwifty-packets/issues
Platform: UNKNOWN
Classifier: Development Status :: 3 - Alpha
Classifier: Programming Language :: Python :: 3
Classifier: License :: OSI Approved :: MIT License
Classifier: Operating System :: Microsoft :: Windows
Classifier: Environment :: MacOS X
Classifier: Environment :: Win32 (MS Windows)
Classifier: Intended Audience :: Developers
Classifier: Operating System :: MacOS
Classifier: Operating System :: Microsoft :: Windows :: Windows 10
Requires-Python: >=3.10
License-File: LICENSE
Requires-Dist: protobuf (>=3.19.4)
Requires-Dist: pcapy-ng-macos (>=1.0.4) ; platform_system == "Darwin"
Requires-Dist: pcapy-ng-win-amd64 (>=1.0.4) ; platform_system == "Windows"
